panamah_sdk/__init__.py
panamah_sdk/admin.py
panamah_sdk/batch.py
panamah_sdk/client.py
panamah_sdk/debug.py
panamah_sdk/exceptions.py
panamah_sdk/nfe.py
panamah_sdk/operation.py
panamah_sdk/processor.py
panamah_sdk/stream.py
panamah_sdk/models/__init__.py
panamah_sdk/models/base.py
panamah_sdk/models/definitions.py
tests/__init__.py
tests/routes.py
tests/server.py
tests/test_admin.py
tests/test_batch.py
tests/test_client.py
tests/test_models.py
tests/test_nfe.py
tests/test_processor.py
tests/test_stream.py
panamah_sdk_python-1.0.4.dist-info/LICENSE
panamah_sdk_python-1.0.4.dist-info/METADATA
panamah_sdk_python-1.0.4.dist-info/WHEEL
panamah_sdk_python-1.0.4.dist-info/top_level.txt
panamah_sdk_python-1.0.4.dist-info/RECORD
