Metadata-Version: 2.1
Name: panamah-sdk-python
Version: 1.0.4
Summary: Panamah Software Development Kit for Python
Home-page: https://github.com/casamagalhaes/panamah-sdk-python
Author: Casa Magalhães
Author-email: contato@casamagalhaes.com.br
License: UNKNOWN
Platform: UNKNOWN
Classifier: Programming Language :: Python :: 3
Classifier: License :: OSI Approved :: MIT License
Classifier: Operating System :: OS Independent
Requires-Dist: certifi (==2019.6.16)
Requires-Dist: chardet (==3.0.4)
Requires-Dist: dictor (==0.1.1)
Requires-Dist: events (==0.3)
Requires-Dist: idna (==2.8)
Requires-Dist: python-dateutil (==2.8.0)
Requires-Dist: requests (==2.22.0)
Requires-Dist: six (==1.12.0)
Requires-Dist: urllib3 (==1.25.3)
Requires-Dist: xmltodict (==0.12.0)
